agui_crewai/__init__.py
agui_crewai/context.py
agui_crewai/crews.py
agui_crewai/endpoint.py
agui_crewai/enterprise.py
agui_crewai/events.py
agui_crewai/sdk.py
agui_crewai/utils.py
agui_crewai-0.1.0.dist-info/METADATA
agui_crewai-0.1.0.dist-info/WHEEL
agui_crewai-0.1.0.dist-info/entry_points.txt
agui_crewai-0.1.0.dist-info/RECORD
