Metadata-Version: 2.1
Name: agui_crewai
Version: 0.1.0
Summary: 
Author: Markus Ecker
Author-email: markus.ecker@gmail.com
Requires-Python: >=3.10,<3.14
Classifier: Programming Language :: Python :: 3
Classifier: Programming Language :: Python :: 3.10
Classifier: Programming Language :: Python :: 3.11
Classifier: Programming Language :: Python :: 3.12
Requires-Dist: ag-ui-protocol (==0.1.5)
Requires-Dist: crewai (>=0.130.0,<0.131.0)
Requires-Dist: fastapi (>=0.115.12,<0.116.0)
Requires-Dist: uvicorn (>=0.34.3,<0.35.0)
